funapi/__init__.py
funodps-0.0.1.dist-info/LICENSE
funodps-0.0.1.dist-info/METADATA
funodps-0.0.1.dist-info/WHEEL
funodps-0.0.1.dist-info/entry_points.txt
funodps-0.0.1.dist-info/top_level.txt
funodps-0.0.1.dist-info/RECORD
