Metadata-Version: 2.1
Name: funodps
Version: 0.0.1
Summary: funodps
Home-page: https://github.com/farfarfun/funodps
Author: bingtao
Author-email: 1007530194@qq.com
License-File: LICENSE
Requires-Dist: funpypi
Requires-Dist: funfile
Requires-Dist: requests
Requires-Dist: tqdm
